telepact/Client.py
telepact/DefaultSerialization.py
telepact/Message.py
telepact/MockServer.py
telepact/MockTelepactSchema.py
telepact/RandomGenerator.py
telepact/Response.py
telepact/Serialization.py
telepact/SerializationError.py
telepact/Serializer.py
telepact/Server.py
telepact/TelepactError.py
telepact/TelepactSchema.py
telepact/TelepactSchemaFiles.py
telepact/TelepactSchemaParseError.py
telepact/TestClient.py
telepact/TypedMessage.py
telepact/__init__.py
telepact/internal/ClientHandleMessage.py
telepact/internal/DeserializeInternal.py
telepact/internal/HandleMessage.py
telepact/internal/ParseRequestMessage.py
telepact/internal/ProcessBytes.py
telepact/internal/SelectStructFields.py
telepact/internal/SerializeInternal.py
telepact/internal/binary/Base64Encoder.py
telepact/internal/binary/BinaryEncoder.py
telepact/internal/binary/BinaryEncoderUnavailableError.py
telepact/internal/binary/BinaryEncoding.py
telepact/internal/binary/BinaryEncodingCache.py
telepact/internal/binary/BinaryEncodingMissing.py
telepact/internal/binary/BinaryPackNode.py
telepact/internal/binary/CannotPack.py
telepact/internal/binary/ClientBase64Decode.py
telepact/internal/binary/ClientBase64Encode.py
telepact/internal/binary/ClientBase64Encoder.py
telepact/internal/binary/ClientBinaryDecode.py
telepact/internal/binary/ClientBinaryEncode.py
telepact/internal/binary/ClientBinaryEncoder.py
telepact/internal/binary/ClientBinaryStrategy.py
telepact/internal/binary/ConstructBinaryEncoding.py
telepact/internal/binary/CreateChecksum.py
telepact/internal/binary/DecodeBody.py
telepact/internal/binary/DecodeKeys.py
telepact/internal/binary/DefaultBinaryEncodingCache.py
telepact/internal/binary/EncodeBody.py
telepact/internal/binary/EncodeKeys.py
telepact/internal/binary/Pack.py
telepact/internal/binary/PackBody.py
telepact/internal/binary/PackList.py
telepact/internal/binary/PackMap.py
telepact/internal/binary/ServerBase64Decode.py
telepact/internal/binary/ServerBase64Encode.py
telepact-1.0.0a174.dist-info/METADATA
telepact-1.0.0a174.dist-info/WHEEL
telepact-1.0.0a174.dist-info/licenses/LICENSE
telepact-1.0.0a174.dist-info/licenses/NOTICE
telepact-1.0.0a174.dist-info/RECORD
