Metadata-Version: 2.4
Name: telepact
Version: 1.0.0a174
Summary: The Python Telepact library
License: Apache-2.0
License-File: LICENSE
License-File: NOTICE
Author: Telepact Authors
Author-email: telepact@googlegroups.com
Requires-Python: >=3.11
Classifier: License :: OSI Approved :: Apache Software License
Classifier: Operating System :: OS Independent
Classifier: Programming Language :: Python :: 3
Classifier: Programming Language :: Python :: 3.11
Classifier: Programming Language :: Python :: 3.12
Classifier: Programming Language :: Python :: 3.13
Classifier: Programming Language :: Python :: 3.14
Requires-Dist: msgpack (>=1.1.1,<2.0.0)
